cli/__init__.py
cli/app.py
comprehensive/__init__.py
comprehensive/app.py
comprehensive/config.py
comprehensive/event.py
comprehensive/libs.py
comprehensive/test.py
comprehensive/utils.py
cp_core-0.3.6.dist-info/METADATA
cp_core-0.3.6.dist-info/WHEEL
cp_core-0.3.6.dist-info/entry_points.txt
cp_core/__init__.py
cp_core/api/__init__.py
cp_core/api/v1.py
cp_core/api/v3.py
cp_core/config.py
cp_core/config.yml
cp_core/exception.py
cp_core/libs/__init__.py
cp_core/libs/comprehensive/__init__.py
cp_core/libs/comprehensive/controller.py
cp_core/libs/comprehensive/forms.py
cp_core/libs/comprehensive/judge.py
cp_core/libs/comprehensive/utils.py
cp_core/libs/comprehensive/validate.py
cp_core/libs/core/__init__.py
cp_core/libs/core/base.py
cp_core/libs/core/checker.py
cp_core/libs/core/exceptions.py
cp_core/libs/core/filter/__init__.py
cp_core/libs/core/filter/check.py
cp_core/libs/core/filter/controller.py
cp_core/libs/core/filter/errors.py
cp_core/libs/core/filter/extract.py
cp_core/libs/core/filter/fileutils.py
cp_core/libs/core/filter/forms.py
cp_core/libs/core/filter/msg.py
cp_core/libs/core/filter/parse/__init__.py
cp_core/libs/core/filter/parse/anko_ac.py
cp_core/libs/core/filter/parse/const.py
cp_core/libs/core/filter/parse/current_reading.py
cp_core/libs/core/filter/parse/date.py
cp_core/libs/core/filter/parse/feature.py
cp_core/libs/core/filter/parse/merge.py
cp_core/libs/core/filter/parse/night.py
cp_core/libs/core/filter/parse/potential.py
cp_core/libs/core/filter/parse/statistic.py
cp_core/libs/core/filter/parse/tests/__init__.py
cp_core/libs/core/filter/parse/tests/merge/__init__.py
cp_core/libs/core/filter/parse/tests/merge/test_merge.py
cp_core/libs/core/filter/parse/tests/merge/test_merge_ac.py
cp_core/libs/core/filter/parse/tests/merge/test_merge_dc.py
cp_core/libs/core/filter/parse/tests/params.py
cp_core/libs/core/filter/parse/tests/test_current_reading.py
cp_core/libs/core/filter/parse/tests/test_date.py
cp_core/libs/core/filter/parse/tests/test_feature.py
cp_core/libs/core/filter/parse/tests/test_night.py
cp_core-0.3.6.dist-info/RECORD
