Metadata-Version: 2.1
Name: cp_core
Version: 0.3.6
Summary: cathodic protection core problem
Author-Email: svtter <svtter@qq.com>
License: not open
Requires-Python: <3.12,>=3.11
Requires-Dist: numpy>=2.1.3
Requires-Dist: pandas>=2.2.3
Requires-Dist: setuptools>=75.0.0
Requires-Dist: loguru>=0.7.2
Requires-Dist: openpyxl>=3.1.0
Requires-Dist: pyinstaller>=6.16.0
Requires-Dist: pydantic>=2.10.2
